greenart/__init__.py
greenart/cli.py
greenart/image.py
greenart-0.0.2.dist-info/DESCRIPTION.rst
greenart-0.0.2.dist-info/METADATA
greenart-0.0.2.dist-info/RECORD
greenart-0.0.2.dist-info/WHEEL
greenart-0.0.2.dist-info/entry_points.txt
greenart-0.0.2.dist-info/metadata.json
greenart-0.0.2.dist-info/top_level.txt
